mpl_sns_viz
