Metadata-Version: 1.0
Name: mpl-sns-viz
Version: 0.1.1
Summary: Creates matplotlib and seaborn visuals
Home-page: https://github.com/ajgiust/mpl_sns_viz
Author: Anthony Giustino
Author-email: UNKNOWN
License: UNKNOWN
Platform: UNKNOWN
